pynspect/__init__.py
pynspect/compilers.py
pynspect/filters.py
pynspect/gparser.py
pynspect/jpath.py
pynspect/lexer.py
pynspect/parsetab.py
pynspect/rules.py
pynspect/traversers.py
pynspect-0.22.dist-info/LICENSE.txt
pynspect-0.22.dist-info/METADATA
pynspect-0.22.dist-info/WHEEL
pynspect-0.22.dist-info/top_level.txt
pynspect-0.22.dist-info/zip-safe
pynspect-0.22.dist-info/RECORD
