Metadata-Version: 2.1
Name: pynspect
Version: 0.22
Summary: Python data inspection library
Home-page: https://pypi.org/project/pynspect/
Author: Jan Mach
Author-email: honza.mach.ml@gmail.com
License: MIT
Project-URL: Documentation, https://709.gitlab-pages.cesnet.cz/mentat/pynspect/master/html/manual.html
Project-URL: Source, https://gitlab.cesnet.cz/709/mentat/pynspect
Project-URL: Tracker, https://gitlab.cesnet.cz/709/mentat/pynspect/-/issues
Keywords: library
Classifier: Development Status :: 4 - Beta
Classifier: License :: OSI Approved :: MIT License
Classifier: Programming Language :: Python
License-File: LICENSE.txt
Requires-Dist: ipranges
Requires-Dist: ply
Requires-Dist: six
